{
  "intelFeed": [
    {
      "priority": "LOW",
      "text": "View the overall status and health of AWS services using the AWS Health Dashboard.",
      "src": "AWS Health",
      "impact": "자동 수집 반영",
      "tsIso": "2026-03-29T13:33:51.373Z",
      "ts": "2026-03-29 13:33",
      "verified": false,
      "sourceCount": 1,
      "_updatedAt": 1774791231373,
      "hash": "df72b252473393587c9f95f15ea1789dcc9d5f529f97944762ace9faef995cea"
    },
    {
      "priority": "HIGH",
      "text": "Travel updates | Help | Emirates — Find out about the latest travel updates and any flight changes or cancellations. We update this page regularly with the most recent travel updates.",
      "src": "Emirates Airlines",
      "impact": "자동 수집 반영",
      "tsIso": "2026-03-29T13:33:50.871Z",
      "ts": "2026-03-29 13:33",
      "verified": false,
      "sourceCount": 1,
      "_updatedAt": 1774791230871,
      "hash": "afcfe70ce2bb73d54b4ff3696ac8ad58d0f9fca4eab0949b8f2cb52fcb3b1af5"
    },
    {
      "priority": "HIGH",
      "text": "Home — The AIM Office provides a range of on-line services to ensure the availability of information required for safety, regularity and efficiency of international and national air navigation.",
      "src": "UAE GCAA",
      "impact": "자동 수집 반영",
      "tsIso": "2026-03-29T13:33:50.448Z",
      "ts": "2026-03-29 13:33",
      "verified": false,
      "sourceCount": 1,
      "_updatedAt": 1774791230448,
      "hash": "c8534c90ecf14483aa999f0003469e7769c39d23b8a667f0ece71dfec1ff0bb4"
    },
    {
      "priority": "HIGH",
      "text": "United Arab Emirates travel advice - GOV.UK — FCDO travel advice for United Arab Emirates. Includes safety and security, insurance, entry requirements and legal differences.",
      "src": "UK FCDO",
      "impact": "자동 수집 반영",
      "tsIso": "2026-03-29T13:33:48.323Z",
      "ts": "2026-03-29 13:33",
      "verified": false,
      "sourceCount": 1,
      "_updatedAt": 1774791228323,
      "hash": "12d5ff68adb712f5f67502e41ca0dd507ea4d6a0170a506fb5079f7cfb5a3329"
    },
    {
      "priority": "HIGH",
      "text": "United Arab Emirates Travel Advisory — Travel Advisories",
      "src": "US State Dept",
      "impact": "자동 수집 반영",
      "tsIso": "2026-03-29T13:33:42.598Z",
      "ts": "2026-03-29 13:33",
      "verified": false,
      "sourceCount": 1,
      "_updatedAt": 1774791222598,
      "hash": "730271d64ec8a61ba9ec102987aef6ba543cefc61391b6e0d5dd3e384b4d4959"
    },
    {
      "priority": "MEDIUM",
      "text": "Iranian attacks across Gulf continue as major industrial sites hit — A number of people are said to have been injured after attacks on aluminium sites in the UAE and Bahrain.",
      "src": "BBC / https://www.bbc.com/news/articles/cp86yrq5jy7o?at_medium=RSS&at_campaign=rss",
      "impact": "자동 수집 반영",
      "tsIso": "2026-03-29T13:32:49.000Z",
      "ts": "2026-03-29 13:32",
      "verified": false,
      "sourceCount": 1,
      "_updatedAt": 1774791169000,
      "hash": "e56946dc93e86e52c31208ff1389716106b87d1bfc8bf5d0f04787f2256a779d"
    },
    {
      "priority": "LOW",
      "text": "View the overall status and health of AWS services using the AWS Health Dashboard.",
      "src": "AWS Health",
      "impact": "자동 수집 반영",
      "tsIso": "2026-03-29T12:29:22.638Z",
      "ts": "2026-03-29 12:29",
      "verified": false,
      "sourceCount": 1,
      "_updatedAt": 1774787362638,
      "hash": "e263f1d44dee2033cf7a8fd843341302cd0f2edbbfe268bb68b6f5636535adf5"
    },
    {
      "priority": "HIGH",
      "text": "Travel updates | Help | Emirates — Find out about the latest travel updates and any flight changes or cancellations. We update this page regularly with the most recent travel updates.",
      "src": "Emirates Airlines",
      "impact": "자동 수집 반영",
      "tsIso": "2026-03-29T12:29:22.178Z",
      "ts": "2026-03-29 12:29",
      "verified": false,
      "sourceCount": 1,
      "_updatedAt": 1774787362178,
      "hash": "2be38ddf40774e6c35e68d9a84a0606614e28ed5074646f02b0afbf56347f8a0"
    },
    {
      "priority": "HIGH",
      "text": "Home — The AIM Office provides a range of on-line services to ensure the availability of information required for safety, regularity and efficiency of international and national air navigation.",
      "src": "UAE GCAA",
      "impact": "자동 수집 반영",
      "tsIso": "2026-03-29T12:29:21.555Z",
      "ts": "2026-03-29 12:29",
      "verified": false,
      "sourceCount": 1,
      "_updatedAt": 1774787361555,
      "hash": "ce19b5844edce488fff0828001fbc163efced87cab3e58619a84c7a3c21eaebb"
    },
    {
      "priority": "HIGH",
      "text": "United Arab Emirates travel advice - GOV.UK — FCDO travel advice for United Arab Emirates. Includes safety and security, insurance, entry requirements and legal differences.",
      "src": "UK FCDO",
      "impact": "자동 수집 반영",
      "tsIso": "2026-03-29T12:29:19.261Z",
      "ts": "2026-03-29 12:29",
      "verified": false,
      "sourceCount": 1,
      "_updatedAt": 1774787359261,
      "hash": "43897ae3849c8490b1570369975ec0cf2f81b6d120581ba07f9582a57abf2039"
    },
    {
      "priority": "HIGH",
      "text": "United Arab Emirates Travel Advisory — Travel Advisories",
      "src": "US State Dept",
      "impact": "자동 수집 반영",
      "tsIso": "2026-03-29T12:29:18.334Z",
      "ts": "2026-03-29 12:29",
      "verified": false,
      "sourceCount": 1,
      "_updatedAt": 1774787358334,
      "hash": "a2b5c6c9e8619be69ced1d5d7a96788b0b55b91319cf50844451c8cfcc01ccac"
    },
    {
      "priority": "HIGH",
      "text": "The US-Israeli war on humanity — The lawlessness and brutality of the US-Israeli genocide in Gaza have now spread to other parts of the world.",
      "src": "Al Jazeera / https://www.aljazeera.com/opinions/2026/3/29/the-us-israeli-war-on-humanity?traffic_source=rss",
      "impact": "자동 수집 반영",
      "tsIso": "2026-03-29T12:08:26.000Z",
      "ts": "2026-03-29 12:08",
      "verified": false,
      "sourceCount": 1,
      "_updatedAt": 1774786106000,
      "hash": "e1c6b7dd9abda75c135c461d4bd96cf0d971dc3581b4ce868fb5a117f8bc17e2"
    }
  ],
  "indicators": [],
  "hypotheses": [],
  "routes": [],
  "checklist": [],
  "metadata": {
    "egressLossETA": 2
  }
}
