{
  "intelFeed": [
    {
      "priority": "LOW",
      "text": "View the overall status and health of AWS services using the AWS Health Dashboard.",
      "src": "AWS Health",
      "impact": "자동 수집 반영",
      "tsIso": "2026-03-30T23:56:14.424Z",
      "ts": "2026-03-30 23:56",
      "verified": false,
      "sourceCount": 1,
      "_updatedAt": 1774914974424,
      "hash": "76acd73903a4afd77755a79bc612707003ea5f0f81b5d3f65d30515325188131"
    },
    {
      "priority": "HIGH",
      "text": "Travel updates | Help | Emirates — Find out about the latest travel updates and any flight changes or cancellations. We update this page regularly with the most recent travel updates.",
      "src": "Emirates Airlines",
      "impact": "자동 수집 반영",
      "tsIso": "2026-03-30T23:56:14.172Z",
      "ts": "2026-03-30 23:56",
      "verified": false,
      "sourceCount": 1,
      "_updatedAt": 1774914974172,
      "hash": "ea716f1a693640847ff86396031eb327ea54fa444c9194148198677942ec96fb"
    },
    {
      "priority": "HIGH",
      "text": "Home — The AIM Office provides a range of on-line services to ensure the availability of information required for safety, regularity and efficiency of international and national air navigation.",
      "src": "UAE GCAA",
      "impact": "자동 수집 반영",
      "tsIso": "2026-03-30T23:56:13.782Z",
      "ts": "2026-03-30 23:56",
      "verified": false,
      "sourceCount": 1,
      "_updatedAt": 1774914973782,
      "hash": "70addc3283b0e04dfc17f2f3e9299ae65684124b24f3805b0de1fa2c2174da42"
    },
    {
      "priority": "HIGH",
      "text": "United Arab Emirates travel advice - GOV.UK — FCDO travel advice for United Arab Emirates. Includes safety and security, insurance, entry requirements and legal differences.",
      "src": "UK FCDO",
      "impact": "자동 수집 반영",
      "tsIso": "2026-03-30T23:56:12.066Z",
      "ts": "2026-03-30 23:56",
      "verified": false,
      "sourceCount": 1,
      "_updatedAt": 1774914972066,
      "hash": "3516328cb98d5232de3556cecc6d1ada78126f6e833de0d87f75122f05e1534e"
    },
    {
      "priority": "HIGH",
      "text": "United Arab Emirates Travel Advisory — Travel Advisories",
      "src": "US State Dept",
      "impact": "자동 수집 반영",
      "tsIso": "2026-03-30T23:56:11.307Z",
      "ts": "2026-03-30 23:56",
      "verified": false,
      "sourceCount": 1,
      "_updatedAt": 1774914971307,
      "hash": "7a4cd4f939b15c66777d146bf8305c72ca957b79fb236c1f59a342805dcee5df"
    },
    {
      "priority": "HIGH",
      "text": "US raises concern over Israel’s closure of Jerusalem holy sites — The White House says the US has raised concerns with Israel over closure of Jerusalem holy sites.",
      "src": "Al Jazeera / https://www.aljazeera.com/video/newsfeed/2026/3/30/us-raises-concern-over-israels-closure-of-jerusalem-holy-sites?traffic_source=rss",
      "impact": "자동 수집 반영",
      "tsIso": "2026-03-30T23:21:37.000Z",
      "ts": "2026-03-30 23:21",
      "verified": false,
      "sourceCount": 1,
      "_updatedAt": 1774912897000,
      "hash": "11f00ecadb77b5737f10e23a231ee23a3df1a318831fe7a323f6ed5a0e4aff5a"
    },
    {
      "priority": "HIGH",
      "text": "Iran’s foreign ministry rejects US ceasefire demands — Iranian Foreign Ministry spokesman says US conditions for a ceasefire are ‘excessive, unrealistic and unreasonable’.",
      "src": "Al Jazeera / https://www.aljazeera.com/video/newsfeed/2026/3/30/irans-foreign-ministry-rejects-us-ceasefire-demands?traffic_source=rss",
      "impact": "자동 수집 반영",
      "tsIso": "2026-03-30T23:12:51.000Z",
      "ts": "2026-03-30 23:12",
      "verified": false,
      "sourceCount": 1,
      "_updatedAt": 1774912371000,
      "hash": "2133b813eaa1d7faa6740a6d067074f115bc6bf7f3034dfc3a75bdb8ee56377a"
    },
    {
      "priority": "LOW",
      "text": "View the overall status and health of AWS services using the AWS Health Dashboard.",
      "src": "AWS Health",
      "impact": "자동 수집 반영",
      "tsIso": "2026-03-30T23:01:14.817Z",
      "ts": "2026-03-30 23:01",
      "verified": false,
      "sourceCount": 1,
      "_updatedAt": 1774911674817,
      "hash": "2af498fed08c294d505ec451b42198680f0f6b006dfe23a547319d58620f9394"
    },
    {
      "priority": "HIGH",
      "text": "Travel updates | Help | Emirates — Find out about the latest travel updates and any flight changes or cancellations. We update this page regularly with the most recent travel updates.",
      "src": "Emirates Airlines",
      "impact": "자동 수집 반영",
      "tsIso": "2026-03-30T23:01:14.641Z",
      "ts": "2026-03-30 23:01",
      "verified": false,
      "sourceCount": 1,
      "_updatedAt": 1774911674641,
      "hash": "d914126b5da24d6d640d3d48df376354a876c10d4cbe4961ab8ff37311fdf04a"
    },
    {
      "priority": "HIGH",
      "text": "Home — The AIM Office provides a range of on-line services to ensure the availability of information required for safety, regularity and efficiency of international and national air navigation.",
      "src": "UAE GCAA",
      "impact": "자동 수집 반영",
      "tsIso": "2026-03-30T23:01:14.241Z",
      "ts": "2026-03-30 23:01",
      "verified": false,
      "sourceCount": 1,
      "_updatedAt": 1774911674241,
      "hash": "27cd25ca2decfb5972fd4a2f85b10a09b1e110da38feaa39c5145acf91176394"
    },
    {
      "priority": "HIGH",
      "text": "United Arab Emirates travel advice - GOV.UK — FCDO travel advice for United Arab Emirates. Includes safety and security, insurance, entry requirements and legal differences.",
      "src": "UK FCDO",
      "impact": "자동 수집 반영",
      "tsIso": "2026-03-30T23:01:12.746Z",
      "ts": "2026-03-30 23:01",
      "verified": false,
      "sourceCount": 1,
      "_updatedAt": 1774911672746,
      "hash": "df7171229a37c18ea3ce8e20519626801e1ea2c30ef3d03ba3bfb619bf75ba45"
    },
    {
      "priority": "HIGH",
      "text": "United Arab Emirates Travel Advisory — Travel Advisories",
      "src": "US State Dept",
      "impact": "자동 수집 반영",
      "tsIso": "2026-03-30T23:01:11.944Z",
      "ts": "2026-03-30 23:01",
      "verified": false,
      "sourceCount": 1,
      "_updatedAt": 1774911671944,
      "hash": "6ce2e17d0d0334b32b56990d80effbf9a8eec98b26c0b3b0d80c2684088e552a"
    }
  ],
  "indicators": [],
  "hypotheses": [],
  "routes": [],
  "checklist": [],
  "metadata": {
    "egressLossETA": 2
  }
}
