{
  "intelFeed": [
    {
      "priority": "LOW",
      "text": "View the overall status and health of AWS services using the AWS Health Dashboard.",
      "src": "AWS Health",
      "impact": "자동 수집 반영",
      "tsIso": "2026-03-28T11:48:29.433Z",
      "ts": "2026-03-28 11:48",
      "verified": false,
      "sourceCount": 1,
      "_updatedAt": 1774698509433,
      "hash": "d6ed7544af5c350f53874cf63aa8c0b1d1f3568663fa7e708830f61ceca605d8"
    },
    {
      "priority": "HIGH",
      "text": "Travel updates | Help | Emirates — Find out about the latest travel updates and any flight changes or cancellations. We update this page regularly with the most recent travel updates.",
      "src": "Emirates Airlines",
      "impact": "자동 수집 반영",
      "tsIso": "2026-03-28T11:48:29.304Z",
      "ts": "2026-03-28 11:48",
      "verified": false,
      "sourceCount": 1,
      "_updatedAt": 1774698509304,
      "hash": "d9300281f2f130bf6303bf21c6185bb2c10a37cb1f755681f377500a9c71d05f"
    },
    {
      "priority": "HIGH",
      "text": "Home — The AIM Office provides a range of on-line services to ensure the availability of information required for safety, regularity and efficiency of international and national air navigation.",
      "src": "UAE GCAA",
      "impact": "자동 수집 반영",
      "tsIso": "2026-03-28T11:48:28.916Z",
      "ts": "2026-03-28 11:48",
      "verified": false,
      "sourceCount": 1,
      "_updatedAt": 1774698508916,
      "hash": "4970aa65dc90734e2390d45020b13b64bd8d7d5d4265f04a036d8d8f547ecdfc"
    },
    {
      "priority": "HIGH",
      "text": "United Arab Emirates travel advice - GOV.UK — FCDO travel advice for United Arab Emirates. Includes safety and security, insurance, entry requirements and legal differences.",
      "src": "UK FCDO",
      "impact": "자동 수집 반영",
      "tsIso": "2026-03-28T11:48:26.622Z",
      "ts": "2026-03-28 11:48",
      "verified": false,
      "sourceCount": 1,
      "_updatedAt": 1774698506622,
      "hash": "19ad590992a343e5dabffe2b1e7870342bbd67690e07e01c6e00ba9dbf09f9a9"
    },
    {
      "priority": "HIGH",
      "text": "United Arab Emirates Travel Advisory — Travel Advisories",
      "src": "US State Dept",
      "impact": "자동 수집 반영",
      "tsIso": "2026-03-28T11:48:25.940Z",
      "ts": "2026-03-28 11:48",
      "verified": false,
      "sourceCount": 1,
      "_updatedAt": 1774698505940,
      "hash": "ea985e72701625b8a76ed9ecd99b9db298453a19ce01ce592bfed188bdbf8468"
    },
    {
      "priority": "LOW",
      "text": "View the overall status and health of AWS services using the AWS Health Dashboard.",
      "src": "AWS Health",
      "impact": "자동 수집 반영",
      "tsIso": "2026-03-28T11:24:11.300Z",
      "ts": "2026-03-28 11:24",
      "verified": false,
      "sourceCount": 1,
      "_updatedAt": 1774697051300,
      "hash": "ca8fe6e546f954d9e595ee4c1285c0db92e92539aac6171581f493ad895deb6d"
    },
    {
      "priority": "HIGH",
      "text": "Travel updates | Help | Emirates — Find out about the latest travel updates and any flight changes or cancellations. We update this page regularly with the most recent travel updates.",
      "src": "Emirates Airlines",
      "impact": "자동 수집 반영",
      "tsIso": "2026-03-28T11:24:11.139Z",
      "ts": "2026-03-28 11:24",
      "verified": false,
      "sourceCount": 1,
      "_updatedAt": 1774697051139,
      "hash": "001be9aea2df4e04fab1f699e15a5d1e39bdb401d73c30ba3af83fc772a28ced"
    },
    {
      "priority": "HIGH",
      "text": "Home — The AIM Office provides a range of on-line services to ensure the availability of information required for safety, regularity and efficiency of international and national air navigation.",
      "src": "UAE GCAA",
      "impact": "자동 수집 반영",
      "tsIso": "2026-03-28T11:24:10.749Z",
      "ts": "2026-03-28 11:24",
      "verified": false,
      "sourceCount": 1,
      "_updatedAt": 1774697050749,
      "hash": "95ea198010007211ee50cc4c74a00a8985f4513d3121ef136b0df941a7a30bf9"
    },
    {
      "priority": "HIGH",
      "text": "United Arab Emirates travel advice - GOV.UK — FCDO travel advice for United Arab Emirates. Includes safety and security, insurance, entry requirements and legal differences.",
      "src": "UK FCDO",
      "impact": "자동 수집 반영",
      "tsIso": "2026-03-28T11:24:09.086Z",
      "ts": "2026-03-28 11:24",
      "verified": false,
      "sourceCount": 1,
      "_updatedAt": 1774697049086,
      "hash": "1c4bb0b6e80e155052032f049c109822cba4bb142b0ff1b7dbe43cb09bbb07ee"
    },
    {
      "priority": "HIGH",
      "text": "United Arab Emirates Travel Advisory — Travel Advisories",
      "src": "US State Dept",
      "impact": "자동 수집 반영",
      "tsIso": "2026-03-28T11:24:08.242Z",
      "ts": "2026-03-28 11:24",
      "verified": false,
      "sourceCount": 1,
      "_updatedAt": 1774697048242,
      "hash": "f1e7ae88520e586f8277f3111a414ba029f2177dc953841495b3b98007f3eb2a"
    },
    {
      "priority": "HIGH",
      "text": "How the US and Israel are making the Islamic republic stronger — The war is feeding into a theological narrative of martyrdom and sacrifice that is helping maintain the Islamic Republic",
      "src": "Al Jazeera / https://www.aljazeera.com/opinions/2026/3/28/how-the-us-and-israel-are-making-the-islamic-republic?traffic_source=rss",
      "impact": "자동 수집 반영",
      "tsIso": "2026-03-28T11:12:32.000Z",
      "ts": "2026-03-28 11:12",
      "verified": false,
      "sourceCount": 1,
      "_updatedAt": 1774696352000,
      "hash": "f26d433fa5c318685ee6b2659b10090283b9a318a717aba5eb38fa6b3b0e38d0"
    },
    {
      "priority": "HIGH",
      "text": "Russian strikes on Ukraine kill 4 as deal to end war dims — US Secretary of State Marco Rubio voices openness to diverting weapons to Kyiv to support the US attack on Iran.",
      "src": "Al Jazeera / https://www.aljazeera.com/news/2026/3/28/russian-strikes-on-ukraine-cities-kill-4-as-deal-to-end-war-dims?traffic_source=rss",
      "impact": "자동 수집 반영",
      "tsIso": "2026-03-28T11:11:48.000Z",
      "ts": "2026-03-28 11:11",
      "verified": false,
      "sourceCount": 1,
      "_updatedAt": 1774696308000,
      "hash": "f7b8bb4886786e262f36537da3baa3b0b18b236de744913ac0f43f8371a8ff89"
    }
  ],
  "indicators": [],
  "hypotheses": [],
  "routes": [],
  "checklist": [],
  "metadata": {
    "egressLossETA": 2
  }
}
