{
  "intelFeed": [
    {
      "priority": "LOW",
      "text": "View the overall status and health of AWS services using the AWS Health Dashboard.",
      "src": "AWS Health",
      "impact": "자동 수집 반영",
      "tsIso": "2026-03-23T22:56:19.411Z",
      "ts": "2026-03-23 22:56",
      "verified": false,
      "sourceCount": 1,
      "_updatedAt": 1774306579411,
      "hash": "4848e0981c46c17a8975ddff9119a97f1ba1b9278c91eb45dcf02b30a7af6d0f"
    },
    {
      "priority": "HIGH",
      "text": "Travel updates | Help | Emirates — Find out about the latest travel updates and any flight changes or cancellations. We update this page regularly with the most recent travel updates.",
      "src": "Emirates Airlines",
      "impact": "자동 수집 반영",
      "tsIso": "2026-03-23T22:56:19.287Z",
      "ts": "2026-03-23 22:56",
      "verified": false,
      "sourceCount": 1,
      "_updatedAt": 1774306579287,
      "hash": "0c198342a6243722a7847c3b936b18a764c481fd70dc5c28cad38ec87e77ad7a"
    },
    {
      "priority": "HIGH",
      "text": "Home — The AIM Office provides a range of on-line services to ensure the availability of information required for safety, regularity and efficiency of international and national air navigation.",
      "src": "UAE GCAA",
      "impact": "자동 수집 반영",
      "tsIso": "2026-03-23T22:56:18.991Z",
      "ts": "2026-03-23 22:56",
      "verified": false,
      "sourceCount": 1,
      "_updatedAt": 1774306578991,
      "hash": "460e54e443cbd8350c84d728cfa1915f4c3731cc8fac5ea2b773fd2635d04adf"
    },
    {
      "priority": "HIGH",
      "text": "United Arab Emirates travel advice - GOV.UK — FCDO travel advice for United Arab Emirates. Includes safety and security, insurance, entry requirements and legal differences.",
      "src": "UK FCDO",
      "impact": "자동 수집 반영",
      "tsIso": "2026-03-23T22:56:17.031Z",
      "ts": "2026-03-23 22:56",
      "verified": false,
      "sourceCount": 1,
      "_updatedAt": 1774306577031,
      "hash": "2bc3716809af7aeaf1e2b090e3b53ee642c118caef08503a2882409e8794fe79"
    },
    {
      "priority": "HIGH",
      "text": "United Arab Emirates Travel Advisory — Travel Advisories",
      "src": "US State Dept",
      "impact": "자동 수집 반영",
      "tsIso": "2026-03-23T22:56:16.037Z",
      "ts": "2026-03-23 22:56",
      "verified": false,
      "sourceCount": 1,
      "_updatedAt": 1774306576037,
      "hash": "79aeee36426ac824421d1d991f50a4b8b5275ef4e94eabb48f5145360d5ecd97"
    },
    {
      "priority": "LOW",
      "text": "View the overall status and health of AWS services using the AWS Health Dashboard.",
      "src": "AWS Health",
      "impact": "자동 수집 반영",
      "tsIso": "2026-03-23T22:20:21.683Z",
      "ts": "2026-03-23 22:20",
      "verified": false,
      "sourceCount": 1,
      "_updatedAt": 1774304421683,
      "hash": "150a0723ee70bcddbab89187a302f9eda24c7f925fb8252cc0500dbcd60a1bb8"
    },
    {
      "priority": "HIGH",
      "text": "Travel updates | Help | Emirates — Find out about the latest travel updates and any flight changes or cancellations. We update this page regularly with the most recent travel updates.",
      "src": "Emirates Airlines",
      "impact": "자동 수집 반영",
      "tsIso": "2026-03-23T22:20:21.466Z",
      "ts": "2026-03-23 22:20",
      "verified": false,
      "sourceCount": 1,
      "_updatedAt": 1774304421466,
      "hash": "ed3403fdaa71512354465b991592af5c06cacdd855c413e3e3f9beec1d7ae888"
    },
    {
      "priority": "HIGH",
      "text": "Home — The AIM Office provides a range of on-line services to ensure the availability of information required for safety, regularity and efficiency of international and national air navigation.",
      "src": "UAE GCAA",
      "impact": "자동 수집 반영",
      "tsIso": "2026-03-23T22:20:20.770Z",
      "ts": "2026-03-23 22:20",
      "verified": false,
      "sourceCount": 1,
      "_updatedAt": 1774304420770,
      "hash": "ec132db75eaa97fbf804f7eb32130917d7818deefd46814454e6915a92365565"
    },
    {
      "priority": "HIGH",
      "text": "United Arab Emirates travel advice - GOV.UK — FCDO travel advice for United Arab Emirates. Includes safety and security, insurance, entry requirements and legal differences.",
      "src": "UK FCDO",
      "impact": "자동 수집 반영",
      "tsIso": "2026-03-23T22:20:19.284Z",
      "ts": "2026-03-23 22:20",
      "verified": false,
      "sourceCount": 1,
      "_updatedAt": 1774304419284,
      "hash": "1ef833658e4a0b59255c84e835a6cdce3afbed487b59b262d9759f548cd3dd9a"
    },
    {
      "priority": "HIGH",
      "text": "United Arab Emirates Travel Advisory — Travel Advisories",
      "src": "US State Dept",
      "impact": "자동 수집 반영",
      "tsIso": "2026-03-23T22:20:18.075Z",
      "ts": "2026-03-23 22:20",
      "verified": false,
      "sourceCount": 1,
      "_updatedAt": 1774304418075,
      "hash": "ffa31d6230558732bc57ef4de7f8b2beafd6f2557f5daa893bea1663533a1b8b"
    },
    {
      "priority": "LOW",
      "text": "View the overall status and health of AWS services using the AWS Health Dashboard.",
      "src": "AWS Health",
      "impact": "자동 수집 반영",
      "tsIso": "2026-03-23T21:53:28.069Z",
      "ts": "2026-03-23 21:53",
      "verified": false,
      "sourceCount": 1,
      "_updatedAt": 1774302808069,
      "hash": "147210c614cc8042a4c98f030b123dc0c7f2358671638a4005db60260ae73c13"
    },
    {
      "priority": "HIGH",
      "text": "Travel updates | Help | Emirates — Find out about the latest travel updates and any flight changes or cancellations. We update this page regularly with the most recent travel updates.",
      "src": "Emirates Airlines",
      "impact": "자동 수집 반영",
      "tsIso": "2026-03-23T21:53:27.926Z",
      "ts": "2026-03-23 21:53",
      "verified": false,
      "sourceCount": 1,
      "_updatedAt": 1774302807926,
      "hash": "c29c0b750f3879f3f9309ad3d528c1d238c4094176bee4a03fbe7c26543fe221"
    }
  ],
  "indicators": [],
  "hypotheses": [],
  "routes": [],
  "checklist": [],
  "metadata": {
    "egressLossETA": 2
  }
}
