{
  "intelFeed": [
    {
      "priority": "LOW",
      "text": "View the overall status and health of AWS services using the AWS Health Dashboard.",
      "src": "AWS Health",
      "impact": "자동 수집 반영",
      "tsIso": "2026-04-28T07:42:27.883Z",
      "ts": "2026-04-28 07:42",
      "verified": false,
      "sourceCount": 1,
      "_updatedAt": 1777362147883,
      "hash": "66e15d207c4594847567a16ca7f240f93f998824aafc6a0394978e81b9ab8aad"
    },
    {
      "priority": "HIGH",
      "text": "Travel updates | Help and Support | Emirates — Find out about the latest travel updates and any flight changes or cancellations. We update this page regularly with the most recent travel updates.",
      "src": "Emirates Airlines",
      "impact": "자동 수집 반영",
      "tsIso": "2026-04-28T07:42:27.660Z",
      "ts": "2026-04-28 07:42",
      "verified": false,
      "sourceCount": 1,
      "_updatedAt": 1777362147660,
      "hash": "84fa465c5ebc89ab6f157332db89aee1547462be7911e8f7c5390428b4104fc0"
    },
    {
      "priority": "HIGH",
      "text": "Home — The AIM Office provides a range of on-line services to ensure the availability of information required for safety, regularity and efficiency of international and national air navigation.",
      "src": "UAE GCAA",
      "impact": "자동 수집 반영",
      "tsIso": "2026-04-28T07:42:27.317Z",
      "ts": "2026-04-28 07:42",
      "verified": false,
      "sourceCount": 1,
      "_updatedAt": 1777362147317,
      "hash": "b917f9b433d38eeb49ee33a58503da3f4c2c423df9763925a33d17bebd250ba5"
    },
    {
      "priority": "HIGH",
      "text": "United Arab Emirates travel advice - GOV.UK — FCDO travel advice for United Arab Emirates. Includes safety and security, insurance, entry requirements and legal differences.",
      "src": "UK FCDO",
      "impact": "자동 수집 반영",
      "tsIso": "2026-04-28T07:42:25.617Z",
      "ts": "2026-04-28 07:42",
      "verified": false,
      "sourceCount": 1,
      "_updatedAt": 1777362145617,
      "hash": "d2ffd61dd8fde3761cff0a54bcc8845155f7e9580c3bbe1efac531a2a43b3945"
    },
    {
      "priority": "HIGH",
      "text": "United Arab Emirates Travel Advisory — Travel Advisories",
      "src": "US State Dept",
      "impact": "자동 수집 반영",
      "tsIso": "2026-04-28T07:42:24.301Z",
      "ts": "2026-04-28 07:42",
      "verified": false,
      "sourceCount": 1,
      "_updatedAt": 1777362144301,
      "hash": "36bf942edbdaf68dc823804cefaead6a91efd79976d786f8ed02123e606d2802"
    },
    {
      "priority": "HIGH",
      "text": "Iran war: What’s happening on day 60 as diplomacy gathers pace? — Trump team reviews Iran peace plan to reopen Hormuz with nuclear talks potentially delayed to a later stage.",
      "src": "Al Jazeera / https://www.aljazeera.com/news/2026/4/28/iran-war-whats-happening-on-day-60-as-diplomacy-gathers-pace?traffic_source=rss",
      "impact": "자동 수집 반영",
      "tsIso": "2026-04-28T07:06:02.000Z",
      "ts": "2026-04-28 07:06",
      "verified": false,
      "sourceCount": 1,
      "_updatedAt": 1777359962000,
      "hash": "60d9570e54cb9bdddff11b667cb952ad5ba34ad07d16f1a3004bbae7f0643523"
    },
    {
      "priority": "HIGH",
      "text": "At least 20 killed in Colombia highway blast — Colombia&#039;s President Gustavo Petro has blamed a &#039;narco-terrorist group&#039;, led by a former FARC fighter, fo",
      "src": "Al Jazeera / https://www.aljazeera.com/news/2026/4/28/at-least-20-killed-in-colombia-highway-blast?traffic_source=rss",
      "impact": "자동 수집 반영",
      "tsIso": "2026-04-28T06:30:58.000Z",
      "ts": "2026-04-28 06:30",
      "verified": false,
      "sourceCount": 1,
      "_updatedAt": 1777357858000,
      "hash": "1c383a70d3a41e7589f0a2c3462a4426178cb47ffdb91abf4263da60c3ce510c"
    },
    {
      "priority": "LOW",
      "text": "View the overall status and health of AWS services using the AWS Health Dashboard.",
      "src": "AWS Health",
      "impact": "자동 수집 반영",
      "tsIso": "2026-04-28T05:20:11.580Z",
      "ts": "2026-04-28 05:20",
      "verified": false,
      "sourceCount": 1,
      "_updatedAt": 1777353611580,
      "hash": "d1b2bc54c0b6ef5c25f31803abfccdd885bb23f4ffff61d643318cad09c71c24"
    },
    {
      "priority": "HIGH",
      "text": "Travel updates | Help and Support | Emirates — Find out about the latest travel updates and any flight changes or cancellations. We update this page regularly with the most recent travel updates.",
      "src": "Emirates Airlines",
      "impact": "자동 수집 반영",
      "tsIso": "2026-04-28T05:20:11.444Z",
      "ts": "2026-04-28 05:20",
      "verified": false,
      "sourceCount": 1,
      "_updatedAt": 1777353611444,
      "hash": "9a8c6d38ed14dd55d6f313f2e0b2c45a4263b063606e2491447fbd06c17fa227"
    },
    {
      "priority": "HIGH",
      "text": "Home — The AIM Office provides a range of on-line services to ensure the availability of information required for safety, regularity and efficiency of international and national air navigation.",
      "src": "UAE GCAA",
      "impact": "자동 수집 반영",
      "tsIso": "2026-04-28T05:20:11.057Z",
      "ts": "2026-04-28 05:20",
      "verified": false,
      "sourceCount": 1,
      "_updatedAt": 1777353611057,
      "hash": "b322293c3314efe120ced00339eae2a4a27d0b5c57b19502ad4e18c37f13d5c8"
    },
    {
      "priority": "HIGH",
      "text": "United Arab Emirates travel advice - GOV.UK — FCDO travel advice for United Arab Emirates. Includes safety and security, insurance, entry requirements and legal differences.",
      "src": "UK FCDO",
      "impact": "자동 수집 반영",
      "tsIso": "2026-04-28T05:20:09.285Z",
      "ts": "2026-04-28 05:20",
      "verified": false,
      "sourceCount": 1,
      "_updatedAt": 1777353609285,
      "hash": "428be06ee506e4c41c52a2a89cfc593e48833cfc87a4dc2ae4f337402f2cd4d2"
    },
    {
      "priority": "HIGH",
      "text": "United Arab Emirates Travel Advisory — Travel Advisories",
      "src": "US State Dept",
      "impact": "자동 수집 반영",
      "tsIso": "2026-04-28T05:20:09.018Z",
      "ts": "2026-04-28 05:20",
      "verified": false,
      "sourceCount": 1,
      "_updatedAt": 1777353609018,
      "hash": "0b4263401b4c851bf30fb58e9f5bc0250d85423f6806faadc05380f63ea5f75a"
    }
  ],
  "indicators": [],
  "hypotheses": [],
  "routes": [],
  "checklist": [],
  "metadata": {
    "egressLossETA": 2
  }
}
