{
  "intelFeed": [
    {
      "priority": "LOW",
      "text": "View the overall status and health of AWS services using the AWS Health Dashboard.",
      "src": "AWS Health",
      "impact": "자동 수집 반영",
      "tsIso": "2026-03-08T21:13:31.443Z",
      "ts": "2026-03-08 21:13",
      "verified": false,
      "sourceCount": 1,
      "_updatedAt": 1773004411443,
      "hash": "609b0d2f32d47e5593552382ab53734f80975b8387c0f46de894101d02d4a53f"
    },
    {
      "priority": "HIGH",
      "text": "Travel updates | Help | Emirates — Find out about the latest travel updates and any flight changes or cancellations. We update this page regularly with the most recent travel updates.",
      "src": "Emirates Airlines",
      "impact": "자동 수집 반영",
      "tsIso": "2026-03-08T21:13:31.133Z",
      "ts": "2026-03-08 21:13",
      "verified": false,
      "sourceCount": 1,
      "_updatedAt": 1773004411133,
      "hash": "9f6cfd294af6c6bc377f52f9b7693518be0fca38b1447c27c9fd9b72a72d78a2"
    },
    {
      "priority": "HIGH",
      "text": "Home — The AIM Office provides a range of on-line services to ensure the availability of information required for safety, regularity and efficiency of international and national air navigation.",
      "src": "UAE GCAA",
      "impact": "자동 수집 반영",
      "tsIso": "2026-03-08T21:13:30.555Z",
      "ts": "2026-03-08 21:13",
      "verified": false,
      "sourceCount": 1,
      "_updatedAt": 1773004410555,
      "hash": "93fd8a64723d5cb89350913f9b220df658cb10ccc449bda0c7144994dd085bd4"
    },
    {
      "priority": "HIGH",
      "text": "United Arab Emirates travel advice - GOV.UK — FCDO travel advice for United Arab Emirates. Includes safety and security, insurance, entry requirements and legal differences.",
      "src": "UK FCDO",
      "impact": "자동 수집 반영",
      "tsIso": "2026-03-08T21:13:28.622Z",
      "ts": "2026-03-08 21:13",
      "verified": false,
      "sourceCount": 1,
      "_updatedAt": 1773004408622,
      "hash": "86238f1c33dc641e857b561da44f583c4fa10f55453473ccb44b8a29c338bbfa"
    },
    {
      "priority": "HIGH",
      "text": "United Arab Emirates Travel Advisory — Travel Advisories",
      "src": "US State Dept",
      "impact": "자동 수집 반영",
      "tsIso": "2026-03-08T21:13:27.578Z",
      "ts": "2026-03-08 21:13",
      "verified": false,
      "sourceCount": 1,
      "_updatedAt": 1773004407578,
      "hash": "b180be5d08f1053012e775f020d179f9a7a5d4b7c330fcc9e8137b624ef9e18a"
    },
    {
      "priority": "LOW",
      "text": "View the overall status and health of AWS services using the AWS Health Dashboard.",
      "src": "AWS Health",
      "impact": "자동 수집 반영",
      "tsIso": "2026-03-08T20:46:03.271Z",
      "ts": "2026-03-08 20:46",
      "verified": false,
      "sourceCount": 1,
      "_updatedAt": 1773002763271,
      "hash": "21da8627eda700bb20bffbce68d8d9d7755c3a4d8d5d223fdfbc2624ce8016a4"
    },
    {
      "priority": "HIGH",
      "text": "Travel updates | Help | Emirates — Find out about the latest travel updates and any flight changes or cancellations. We update this page regularly with the most recent travel updates.",
      "src": "Emirates Airlines",
      "impact": "자동 수집 반영",
      "tsIso": "2026-03-08T20:46:03.120Z",
      "ts": "2026-03-08 20:46",
      "verified": false,
      "sourceCount": 1,
      "_updatedAt": 1773002763120,
      "hash": "e58cad78baf5d546a01bd35587bfbdbcc27930d3d272bd85bac2c8abf98e4234"
    },
    {
      "priority": "HIGH",
      "text": "Home — The AIM Office provides a range of on-line services to ensure the availability of information required for safety, regularity and efficiency of international and national air navigation.",
      "src": "UAE GCAA",
      "impact": "자동 수집 반영",
      "tsIso": "2026-03-08T20:46:02.828Z",
      "ts": "2026-03-08 20:46",
      "verified": false,
      "sourceCount": 1,
      "_updatedAt": 1773002762828,
      "hash": "0971b6d3c2850f7e083fab93bdbb049ef05cdeec81bb139a87252fab9e6d19c4"
    },
    {
      "priority": "HIGH",
      "text": "United Arab Emirates travel advice - GOV.UK — FCDO travel advice for United Arab Emirates. Includes safety and security, insurance, entry requirements and legal differences.",
      "src": "UK FCDO",
      "impact": "자동 수집 반영",
      "tsIso": "2026-03-08T20:46:00.783Z",
      "ts": "2026-03-08 20:46",
      "verified": false,
      "sourceCount": 1,
      "_updatedAt": 1773002760783,
      "hash": "d975b5eee7b98ad776e836d31eab3536cac737a1384d1962ba3b662bd8d81f8d"
    },
    {
      "priority": "HIGH",
      "text": "United Arab Emirates Travel Advisory — Travel Advisories",
      "src": "US State Dept",
      "impact": "자동 수집 반영",
      "tsIso": "2026-03-08T20:46:00.013Z",
      "ts": "2026-03-08 20:46",
      "verified": false,
      "sourceCount": 1,
      "_updatedAt": 1773002760013,
      "hash": "ac07969fa05c036b8225dc76579f628c3f397c466e0157a058fa4977cacf8c04"
    },
    {
      "priority": "HIGH",
      "text": "Thousands flee Akobo after South Sudan army issues forced evacuation order — Army tells UN and aid workers to leave as forces close in on one of the last opposition strongholds.",
      "src": "Al Jazeera / https://www.aljazeera.com/news/2026/3/8/thousands-flee-akobo-after-south-sudan-army-issues-forced-evacuation-order?traffic_source=rss",
      "impact": "자동 수집 반영",
      "tsIso": "2026-03-08T20:17:38.000Z",
      "ts": "2026-03-08 20:17",
      "verified": false,
      "sourceCount": 1,
      "_updatedAt": 1773001058000,
      "hash": "899c089fc5c759bcd11452b45a913de1e644906b734d683161e1f59506ba261a"
    },
    {
      "priority": "LOW",
      "text": "View the overall status and health of AWS services using the AWS Health Dashboard.",
      "src": "AWS Health",
      "impact": "자동 수집 반영",
      "tsIso": "2026-03-08T20:13:36.570Z",
      "ts": "2026-03-08 20:13",
      "verified": false,
      "sourceCount": 1,
      "_updatedAt": 1773000816570,
      "hash": "1c7b8846200febe27a88b1e4b81fc8ef2d028ca625a0d8306ff5fd328ff78b43"
    }
  ],
  "indicators": [],
  "hypotheses": [],
  "routes": [],
  "checklist": [],
  "metadata": {
    "egressLossETA": 2
  }
}
