{
  "intelFeed": [
    {
      "priority": "LOW",
      "text": "View the overall status and health of AWS services using the AWS Health Dashboard.",
      "src": "AWS Health",
      "impact": "자동 수집 반영",
      "tsIso": "2026-03-31T23:54:14.376Z",
      "ts": "2026-03-31 23:54",
      "verified": false,
      "sourceCount": 1,
      "_updatedAt": 1775001254376,
      "hash": "39e2534e8b09c7f10809bb6a00bf5d9ec4fd44b8ef38dcb5bb3f9425b30354ef"
    },
    {
      "priority": "HIGH",
      "text": "Travel updates | Help | Emirates — Find out about the latest travel updates and any flight changes or cancellations. We update this page regularly with the most recent travel updates.",
      "src": "Emirates Airlines",
      "impact": "자동 수집 반영",
      "tsIso": "2026-03-31T23:54:14.116Z",
      "ts": "2026-03-31 23:54",
      "verified": false,
      "sourceCount": 1,
      "_updatedAt": 1775001254116,
      "hash": "f962dec86dac8d6c3fc2c24421148eb556d9b393e29ee204120027d5db8a9fba"
    },
    {
      "priority": "HIGH",
      "text": "Home — The AIM Office provides a range of on-line services to ensure the availability of information required for safety, regularity and efficiency of international and national air navigation.",
      "src": "UAE GCAA",
      "impact": "자동 수집 반영",
      "tsIso": "2026-03-31T23:54:13.812Z",
      "ts": "2026-03-31 23:54",
      "verified": false,
      "sourceCount": 1,
      "_updatedAt": 1775001253812,
      "hash": "05e93e54c9193ca6b90b1db3d71478ba96179cab9df8b38b0a1ed387a87d653f"
    },
    {
      "priority": "HIGH",
      "text": "United Arab Emirates travel advice - GOV.UK — FCDO travel advice for United Arab Emirates. Includes safety and security, insurance, entry requirements and legal differences.",
      "src": "UK FCDO",
      "impact": "자동 수집 반영",
      "tsIso": "2026-03-31T23:54:11.830Z",
      "ts": "2026-03-31 23:54",
      "verified": false,
      "sourceCount": 1,
      "_updatedAt": 1775001251830,
      "hash": "8f6187a3b38009e381af2558596a0ff649df62bd005419d62ab472e1d5a1c3bc"
    },
    {
      "priority": "HIGH",
      "text": "United Arab Emirates Travel Advisory — Travel Advisories",
      "src": "US State Dept",
      "impact": "자동 수집 반영",
      "tsIso": "2026-03-31T23:54:10.516Z",
      "ts": "2026-03-31 23:54",
      "verified": false,
      "sourceCount": 1,
      "_updatedAt": 1775001250516,
      "hash": "fa04e5fb861d936fa5fc7944eebcb1443fde83823225f85491030fc48f0223fd"
    },
    {
      "priority": "LOW",
      "text": "View the overall status and health of AWS services using the AWS Health Dashboard.",
      "src": "AWS Health",
      "impact": "자동 수집 반영",
      "tsIso": "2026-03-31T23:23:44.067Z",
      "ts": "2026-03-31 23:23",
      "verified": false,
      "sourceCount": 1,
      "_updatedAt": 1774999424067,
      "hash": "c58b2255181a8259f9891e7e44d081d1185c8c53eca17e35635a23c53ddd9418"
    },
    {
      "priority": "HIGH",
      "text": "Travel updates | Help | Emirates — Find out about the latest travel updates and any flight changes or cancellations. We update this page regularly with the most recent travel updates.",
      "src": "Emirates Airlines",
      "impact": "자동 수집 반영",
      "tsIso": "2026-03-31T23:23:43.938Z",
      "ts": "2026-03-31 23:23",
      "verified": false,
      "sourceCount": 1,
      "_updatedAt": 1774999423938,
      "hash": "b16cdf0b2334bd0247b984284c080812ee62cf0b6cafbdda3ef4f10c34408331"
    },
    {
      "priority": "HIGH",
      "text": "Home — The AIM Office provides a range of on-line services to ensure the availability of information required for safety, regularity and efficiency of international and national air navigation.",
      "src": "UAE GCAA",
      "impact": "자동 수집 반영",
      "tsIso": "2026-03-31T23:23:43.624Z",
      "ts": "2026-03-31 23:23",
      "verified": false,
      "sourceCount": 1,
      "_updatedAt": 1774999423624,
      "hash": "b262ca3d55849f47adc5205161e146bb88c80aebf061423a879e46c6c9d357fb"
    },
    {
      "priority": "HIGH",
      "text": "United Arab Emirates travel advice - GOV.UK — FCDO travel advice for United Arab Emirates. Includes safety and security, insurance, entry requirements and legal differences.",
      "src": "UK FCDO",
      "impact": "자동 수집 반영",
      "tsIso": "2026-03-31T23:23:41.564Z",
      "ts": "2026-03-31 23:23",
      "verified": false,
      "sourceCount": 1,
      "_updatedAt": 1774999421564,
      "hash": "b7cb68d5b8c07efa8f6e55a3f47984f04cf66c604f8f3d2c2b28d48887bacb3c"
    },
    {
      "priority": "HIGH",
      "text": "United Arab Emirates Travel Advisory — Travel Advisories",
      "src": "US State Dept",
      "impact": "자동 수집 반영",
      "tsIso": "2026-03-31T23:23:40.802Z",
      "ts": "2026-03-31 23:23",
      "verified": false,
      "sourceCount": 1,
      "_updatedAt": 1774999420802,
      "hash": "2dc882521d1bbb5749759fa0adf0cd772b387a8628b3b13fa1cdbf168f76fc8d"
    },
    {
      "priority": "HIGH",
      "text": "Pope Leo urges Trump to end war on Iran — Pope Leo XIV has urged US President Donald Trump to find an “off-ramp” from the US and Israel’s war on Iran.",
      "src": "Al Jazeera / https://www.aljazeera.com/video/newsfeed/2026/3/31/pope-leo-urges-trump-to-end-war-on-iran?traffic_source=rss",
      "impact": "자동 수집 반영",
      "tsIso": "2026-03-31T23:12:43.000Z",
      "ts": "2026-03-31 23:12",
      "verified": false,
      "sourceCount": 1,
      "_updatedAt": 1774998763000,
      "hash": "4122873dceeabf99022f3cb0543a45c39b9fada2d70ff7cfb476c748c837ef6b"
    },
    {
      "priority": "HIGH",
      "text": "US exempts Gulf of Mexico oil drillers from endangered species protections — The Trump administration says protections would diminish US energy competitiveness amid the ongoing war on Iran.",
      "src": "Al Jazeera / https://www.aljazeera.com/news/2026/3/31/us-exempts-gulf-of-mexico-oil-drillers-from-endangered-species-protections?traffic_source=rss",
      "impact": "자동 수집 반영",
      "tsIso": "2026-03-31T23:02:56.000Z",
      "ts": "2026-03-31 23:02",
      "verified": false,
      "sourceCount": 1,
      "_updatedAt": 1774998176000,
      "hash": "7365dd201fcd6a903f1b9d6a3d96616604576bb4f084f2eca2e7bd2e7aaf5632"
    }
  ],
  "indicators": [],
  "hypotheses": [],
  "routes": [],
  "checklist": [],
  "metadata": {
    "egressLossETA": 2
  }
}
