{
  "intelFeed": [
    {
      "priority": "LOW",
      "text": "View the overall status and health of AWS services using the AWS Health Dashboard.",
      "src": "AWS Health",
      "impact": "자동 수집 반영",
      "tsIso": "2026-04-08T20:06:04.950Z",
      "ts": "2026-04-08 20:06",
      "verified": false,
      "sourceCount": 1,
      "_updatedAt": 1775678764950,
      "hash": "14c480543043797ab22d77ecb15b2fc2e75319a1ca8be575a92a01210a8ebf64"
    },
    {
      "priority": "HIGH",
      "text": "Travel updates | Help | Emirates — Find out about the latest travel updates and any flight changes or cancellations. We update this page regularly with the most recent travel updates.",
      "src": "Emirates Airlines",
      "impact": "자동 수집 반영",
      "tsIso": "2026-04-08T20:06:04.670Z",
      "ts": "2026-04-08 20:06",
      "verified": false,
      "sourceCount": 1,
      "_updatedAt": 1775678764670,
      "hash": "1ba8a787cd4f36513007c949591462a450372058a24814331221867d2223387a"
    },
    {
      "priority": "HIGH",
      "text": "Home — The AIM Office provides a range of on-line services to ensure the availability of information required for safety, regularity and efficiency of international and national air navigation.",
      "src": "UAE GCAA",
      "impact": "자동 수집 반영",
      "tsIso": "2026-04-08T20:06:03.719Z",
      "ts": "2026-04-08 20:06",
      "verified": false,
      "sourceCount": 1,
      "_updatedAt": 1775678763719,
      "hash": "c6a3a5f0b2218e0b0dc2556676187cd307c8d96590e5340b2b82ae537d21ca5d"
    },
    {
      "priority": "HIGH",
      "text": "United Arab Emirates travel advice - GOV.UK — FCDO travel advice for United Arab Emirates. Includes safety and security, insurance, entry requirements and legal differences.",
      "src": "UK FCDO",
      "impact": "자동 수집 반영",
      "tsIso": "2026-04-08T20:06:01.569Z",
      "ts": "2026-04-08 20:06",
      "verified": false,
      "sourceCount": 1,
      "_updatedAt": 1775678761569,
      "hash": "ae8100f0bd7989c71823f865bf312b2b5e4879687d97d52a743fbcd4434097b1"
    },
    {
      "priority": "HIGH",
      "text": "United Arab Emirates Travel Advisory — Travel Advisories",
      "src": "US State Dept",
      "impact": "자동 수집 반영",
      "tsIso": "2026-04-08T20:06:01.366Z",
      "ts": "2026-04-08 20:06",
      "verified": false,
      "sourceCount": 1,
      "_updatedAt": 1775678761366,
      "hash": "9c1f177a4554529dbe7f19cf95b3cd2168576fb90830290a099988456e059e98"
    },
    {
      "priority": "MEDIUM",
      "text": "U.S. has violated ceasefire agreement, Iran parliamentary speaker says — The two-week ceasefire agreement between the U.S. and Iran appeared at risk of unraveling less than a day after it was a",
      "src": "CNBC / https://www.cnbc.com/2026/04/08/ceasefire-iran-war-lebanon.html",
      "impact": "자동 수집 반영",
      "tsIso": "2026-04-08T20:02:14.000Z",
      "ts": "2026-04-08 20:02",
      "verified": false,
      "sourceCount": 1,
      "_updatedAt": 1775678534000,
      "hash": "e4bb40830731449e0c310ae3b48d7ba30917a39338857599ddda6701e7c1460f"
    },
    {
      "priority": "MEDIUM",
      "text": "More than 100 killed in Lebanon as Israel carries out large wave of strikes — Attacks hit the southern suburbs of Beirut, southern Lebanon and the eastern Bekaa Valley, hours after a US-Iran ceasefi",
      "src": "BBC / https://www.bbc.com/news/articles/c0j6d538l6qo?at_medium=RSS&at_campaign=rss",
      "impact": "자동 수집 반영",
      "tsIso": "2026-04-08T19:50:55.000Z",
      "ts": "2026-04-08 19:50",
      "verified": false,
      "sourceCount": 1,
      "_updatedAt": 1775677855000,
      "hash": "5be71edbc2325ee5ab0ee120eaa59ce827924670a8775955a35ce02a492506a8"
    },
    {
      "priority": "HIGH",
      "text": "World reacts to ‘brutal’ Israeli attacks on Lebanon amid US-Iran ceasefire — Israeli attacks have killed at least 254 people and wounded 1,165 others, according to Lebanon’s Civil Defence.",
      "src": "Al Jazeera / https://www.aljazeera.com/news/2026/4/8/world-reacts-to-brutal-israeli-attacks-on-lebanon-amid-us-iran-ceasefire?traffic_source=rss",
      "impact": "자동 수집 반영",
      "tsIso": "2026-04-08T19:47:57.000Z",
      "ts": "2026-04-08 19:47",
      "verified": false,
      "sourceCount": 1,
      "_updatedAt": 1775677677000,
      "hash": "6277d6c38eb10a9120589d920d0564a32a27ef510d3d6ecbeb5f2c810b21915f"
    },
    {
      "priority": "MEDIUM",
      "text": "Rep. Ritchie Torres calls for probe into futures trades placed ahead March pause on Iran hostilities — Oil and energy futures trading before President Donald Trump announced a pause in Iran attacks in",
      "src": "CNBC / https://www.cnbc.com/2026/04/08/iran-ceasefire-futures-markets-ritchie-torrres.html",
      "impact": "자동 수집 반영",
      "tsIso": "2026-04-08T19:43:18.000Z",
      "ts": "2026-04-08 19:43",
      "verified": false,
      "sourceCount": 1,
      "_updatedAt": 1775677398000,
      "hash": "c4c28363d8fee8a6b476ad873c7729dd68f8e1cb73cdc49361000f710e2cefab"
    },
    {
      "priority": "HIGH",
      "text": "Iranians breathe a ‘ceasefire’ sigh of relief as all sides claim victory — Celebration and scepticism coexist in Tehran as ceasefire offers reprieve despite doubts about its durability.",
      "src": "Al Jazeera / https://www.aljazeera.com/news/2026/4/8/iranians-breathe-a-ceasefire-sigh-of-relief-as-all-sides-claim-victory?traffic_source=rss",
      "impact": "자동 수집 반영",
      "tsIso": "2026-04-08T19:20:34.000Z",
      "ts": "2026-04-08 19:20",
      "verified": false,
      "sourceCount": 1,
      "_updatedAt": 1775676034000,
      "hash": "2bc2c6e0f12847391e57994bc41b04520408a2beb5667b77f0ce274451e6b4a5"
    },
    {
      "priority": "LOW",
      "text": "View the overall status and health of AWS services using the AWS Health Dashboard.",
      "src": "AWS Health",
      "impact": "자동 수집 반영",
      "tsIso": "2026-04-08T19:05:55.370Z",
      "ts": "2026-04-08 19:05",
      "verified": false,
      "sourceCount": 1,
      "_updatedAt": 1775675155370,
      "hash": "51cd012a4305a48dd903e1d33329055cfda764f26802604a639c5fba00442ff8"
    },
    {
      "priority": "HIGH",
      "text": "Travel updates | Help | Emirates — Find out about the latest travel updates and any flight changes or cancellations. We update this page regularly with the most recent travel updates.",
      "src": "Emirates Airlines",
      "impact": "자동 수집 반영",
      "tsIso": "2026-04-08T19:05:55.012Z",
      "ts": "2026-04-08 19:05",
      "verified": false,
      "sourceCount": 1,
      "_updatedAt": 1775675155012,
      "hash": "796245ec7d18dd0c96da45295a1f0aa1f79c5cc778384ab6d95fd1c5dcef38a7"
    }
  ],
  "indicators": [],
  "hypotheses": [],
  "routes": [],
  "checklist": [],
  "metadata": {
    "egressLossETA": 2
  }
}
