{
  "intelFeed": [
    {
      "priority": "LOW",
      "text": "View the overall status and health of AWS services using the AWS Health Dashboard.",
      "src": "AWS Health",
      "impact": "자동 수집 반영",
      "tsIso": "2026-04-13T17:50:18.347Z",
      "ts": "2026-04-13 17:50",
      "verified": false,
      "sourceCount": 1,
      "_updatedAt": 1776102618347,
      "hash": "0a6d7fc58f073db3bbb8f9576edaae60fd69083f159fbe289fbceebfbb6ba455"
    },
    {
      "priority": "HIGH",
      "text": "Travel updates | Help | Emirates — Find out about the latest travel updates and any flight changes or cancellations. We update this page regularly with the most recent travel updates.",
      "src": "Emirates Airlines",
      "impact": "자동 수집 반영",
      "tsIso": "2026-04-13T17:50:18.008Z",
      "ts": "2026-04-13 17:50",
      "verified": false,
      "sourceCount": 1,
      "_updatedAt": 1776102618008,
      "hash": "32dbce7bee3ef47ff40d85cc0c439153e2f305557e8d6a8ac505c522db577acd"
    },
    {
      "priority": "HIGH",
      "text": "Home — The AIM Office provides a range of on-line services to ensure the availability of information required for safety, regularity and efficiency of international and national air navigation.",
      "src": "UAE GCAA",
      "impact": "자동 수집 반영",
      "tsIso": "2026-04-13T17:50:17.355Z",
      "ts": "2026-04-13 17:50",
      "verified": false,
      "sourceCount": 1,
      "_updatedAt": 1776102617355,
      "hash": "a953b79fcf7a3c8779aa397fa00f36ff33348815b6bd5cf42592ead3a387a6f7"
    },
    {
      "priority": "HIGH",
      "text": "United Arab Emirates travel advice - GOV.UK — FCDO travel advice for United Arab Emirates. Includes safety and security, insurance, entry requirements and legal differences.",
      "src": "UK FCDO",
      "impact": "자동 수집 반영",
      "tsIso": "2026-04-13T17:50:11.189Z",
      "ts": "2026-04-13 17:50",
      "verified": false,
      "sourceCount": 1,
      "_updatedAt": 1776102611189,
      "hash": "cb6e2900c3c174853df54dee596a17633f519b857e9ee8050fabb83693977bcf"
    },
    {
      "priority": "HIGH",
      "text": "United Arab Emirates Travel Advisory — Travel Advisories",
      "src": "US State Dept",
      "impact": "자동 수집 반영",
      "tsIso": "2026-04-13T17:50:09.681Z",
      "ts": "2026-04-13 17:50",
      "verified": false,
      "sourceCount": 1,
      "_updatedAt": 1776102609681,
      "hash": "32d70a23c044a5a2970b2713e60ea34327d449907edb896087d64a8a97166be6"
    },
    {
      "priority": "HIGH",
      "text": "EU: No peace possible while “Lebanon is in flames” — Von der Leyen warns Hormuz closure and Israeli strikes on Lebanon threaten regional stability.",
      "src": "Al Jazeera / https://www.aljazeera.com/video/newsfeed/2026/4/13/eu-no-peace-possible-while-lebanon-is-in?traffic_source=rss",
      "impact": "자동 수집 반영",
      "tsIso": "2026-04-13T17:28:22.000Z",
      "ts": "2026-04-13 17:28",
      "verified": false,
      "sourceCount": 1,
      "_updatedAt": 1776101302000,
      "hash": "cc515ab3fd5c9bef5dbb6372239c614ac98e73d215b4e2ffbf33d0f0b4d558eb"
    },
    {
      "priority": "HIGH",
      "text": "What are the pros and cons of Trump’s Iranian naval blockade? — What does Donald Trump’s naval blockade of Iranian ports look like and can it achieve what the US president wants?",
      "src": "Al Jazeera / https://www.aljazeera.com/video/newsfeed/2026/4/13/what-are-the-pros-and-cons-of-trumps-iranian-naval-blockade?traffic_source=rss",
      "impact": "자동 수집 반영",
      "tsIso": "2026-04-13T17:15:02.000Z",
      "ts": "2026-04-13 17:15",
      "verified": false,
      "sourceCount": 1,
      "_updatedAt": 1776100502000,
      "hash": "35747b5083a513c19b2c62247270e5604b86a3f88395983cee1a57da2c9f5f51"
    },
    {
      "priority": "HIGH",
      "text": "Bahrain summons Iraqi envoy as pro-Iranian attacks persist in Gulf — Move reflects regional alarm over attacks by pro-Iranian groups based in Iraq, which continue despite ceasefire.",
      "src": "Al Jazeera / https://www.aljazeera.com/news/2026/4/13/bahrain-summons-iraqi-envoy-as-pro-iranian-attacks-persist-in-gulf?traffic_source=rss",
      "impact": "자동 수집 반영",
      "tsIso": "2026-04-13T16:58:09.000Z",
      "ts": "2026-04-13 16:58",
      "verified": false,
      "sourceCount": 1,
      "_updatedAt": 1776099489000,
      "hash": "d52db04d1dfdb417b2dd944dfbce897186d997dc8ff37501447468b3f7fb1edf"
    },
    {
      "priority": "LOW",
      "text": "View the overall status and health of AWS services using the AWS Health Dashboard.",
      "src": "AWS Health",
      "impact": "자동 수집 반영",
      "tsIso": "2026-04-13T16:52:15.115Z",
      "ts": "2026-04-13 16:52",
      "verified": false,
      "sourceCount": 1,
      "_updatedAt": 1776099135115,
      "hash": "78d0b9a14974b44ff169efb45b7d01b0700b89237ede5c6a4d1d5e0538d144fe"
    },
    {
      "priority": "HIGH",
      "text": "Travel updates | Help | Emirates — Find out about the latest travel updates and any flight changes or cancellations. We update this page regularly with the most recent travel updates.",
      "src": "Emirates Airlines",
      "impact": "자동 수집 반영",
      "tsIso": "2026-04-13T16:52:15.009Z",
      "ts": "2026-04-13 16:52",
      "verified": false,
      "sourceCount": 1,
      "_updatedAt": 1776099135009,
      "hash": "29177dfdca2bb4d09a2c5e03436cb419f9c0991a9e82e35ffaf45ff58a8da036"
    },
    {
      "priority": "HIGH",
      "text": "Home — The AIM Office provides a range of on-line services to ensure the availability of information required for safety, regularity and efficiency of international and national air navigation.",
      "src": "UAE GCAA",
      "impact": "자동 수집 반영",
      "tsIso": "2026-04-13T16:52:14.609Z",
      "ts": "2026-04-13 16:52",
      "verified": false,
      "sourceCount": 1,
      "_updatedAt": 1776099134609,
      "hash": "29196e678f368e954489274a733eebfeebdd86d9a535077c362e3b9f26c82a95"
    },
    {
      "priority": "HIGH",
      "text": "United Arab Emirates travel advice - GOV.UK — FCDO travel advice for United Arab Emirates. Includes safety and security, insurance, entry requirements and legal differences.",
      "src": "UK FCDO",
      "impact": "자동 수집 반영",
      "tsIso": "2026-04-13T16:52:12.955Z",
      "ts": "2026-04-13 16:52",
      "verified": false,
      "sourceCount": 1,
      "_updatedAt": 1776099132955,
      "hash": "1f656a75724ae2ec880256474412b8857c736425a0c1e6efd008327889b5893b"
    }
  ],
  "indicators": [],
  "hypotheses": [],
  "routes": [],
  "checklist": [],
  "metadata": {
    "egressLossETA": 2
  }
}
