{
  "intelFeed": [
    {
      "priority": "LOW",
      "text": "View the overall status and health of AWS services using the AWS Health Dashboard.",
      "src": "AWS Health",
      "impact": "자동 수집 반영",
      "tsIso": "2026-03-06T08:24:25.497Z",
      "ts": "2026-03-06 08:24",
      "verified": false,
      "sourceCount": 1,
      "_updatedAt": 1772785465497,
      "hash": "569c0695883ff282d14b61edf05d635c95b148370fc27ba3607b23b05a976d06"
    },
    {
      "priority": "HIGH",
      "text": "Travel updates | Help | Emirates — Find out about the latest travel updates and any flight changes or cancellations. We update this page regularly with the most recent travel updates.",
      "src": "Emirates Airlines",
      "impact": "자동 수집 반영",
      "tsIso": "2026-03-06T08:24:25.422Z",
      "ts": "2026-03-06 08:24",
      "verified": false,
      "sourceCount": 1,
      "_updatedAt": 1772785465422,
      "hash": "47fb309e315e9c63eb9d7fbe00739bbeeee8b77aed259dda64a4fcff5d4a7638"
    },
    {
      "priority": "HIGH",
      "text": "Home — The AIM Office provides a range of on-line services to ensure the availability of information required for safety, regularity and efficiency of international and national air navigation.",
      "src": "UAE GCAA",
      "impact": "자동 수집 반영",
      "tsIso": "2026-03-06T08:24:25.054Z",
      "ts": "2026-03-06 08:24",
      "verified": false,
      "sourceCount": 1,
      "_updatedAt": 1772785465054,
      "hash": "4066ba10f7c82ae7dddcd62294e1efb4d16c2af707a9ea7600c9c43231878492"
    },
    {
      "priority": "HIGH",
      "text": "United Arab Emirates travel advice - GOV.UK — FCDO travel advice for United Arab Emirates. Includes safety and security, insurance, entry requirements and legal differences.",
      "src": "UK FCDO",
      "impact": "자동 수집 반영",
      "tsIso": "2026-03-06T08:24:23.445Z",
      "ts": "2026-03-06 08:24",
      "verified": false,
      "sourceCount": 1,
      "_updatedAt": 1772785463445,
      "hash": "01f3fcdaf7108b4d82cc12810cbfe0c8a35a4741bb06b3fd85b4ddad5790110a"
    },
    {
      "priority": "HIGH",
      "text": "United Arab Emirates Travel Advisory — Travel Advisories",
      "src": "US State Dept",
      "impact": "자동 수집 반영",
      "tsIso": "2026-03-06T08:24:23.194Z",
      "ts": "2026-03-06 08:24",
      "verified": false,
      "sourceCount": 1,
      "_updatedAt": 1772785463194,
      "hash": "bde84fdb01b8e4394420530e4fa23238ffdd6e65b499dba979c865d901d68207"
    },
    {
      "priority": "HIGH",
      "text": "Anger in Cyprus over UK bases as US-Israel war with Iran endangers island — Protests grow as attack on British military site stirs fears that Cyprus is being dragged into a regional conflict.",
      "src": "Al Jazeera / https://www.aljazeera.com/features/2026/3/6/anger-in-cyprus-over-uk-bases-as-us-israel-war-with-iran-endangers-island?traffic_source=rss",
      "impact": "자동 수집 반영",
      "tsIso": "2026-03-06T08:03:18.000Z",
      "ts": "2026-03-06 08:03",
      "verified": false,
      "sourceCount": 1,
      "_updatedAt": 1772784198000,
      "hash": "87bb58d12e56a4900558b91a788228248f0c7fabc4762167f7ad3eb47e22ad2a"
    },
    {
      "priority": "LOW",
      "text": "View the overall status and health of AWS services using the AWS Health Dashboard.",
      "src": "AWS Health",
      "impact": "자동 수집 반영",
      "tsIso": "2026-03-06T07:55:09.717Z",
      "ts": "2026-03-06 07:55",
      "verified": false,
      "sourceCount": 1,
      "_updatedAt": 1772783709717,
      "hash": "dfa09f1536ff43f993f8c2c825d7c6f60b6b462103fc4f05180d3c508b04ed69"
    },
    {
      "priority": "HIGH",
      "text": "Travel updates | Help | Emirates — Find out about the latest travel updates and any flight changes or cancellations. We update this page regularly with the most recent travel updates.",
      "src": "Emirates Airlines",
      "impact": "자동 수집 반영",
      "tsIso": "2026-03-06T07:55:09.395Z",
      "ts": "2026-03-06 07:55",
      "verified": false,
      "sourceCount": 1,
      "_updatedAt": 1772783709395,
      "hash": "e9354c50844afa9bede25527ae0389edfe76d3ed4a1076edda327f7c0edf2fb4"
    },
    {
      "priority": "HIGH",
      "text": "Home — The AIM Office provides a range of on-line services to ensure the availability of information required for safety, regularity and efficiency of international and national air navigation.",
      "src": "UAE GCAA",
      "impact": "자동 수집 반영",
      "tsIso": "2026-03-06T07:55:09.057Z",
      "ts": "2026-03-06 07:55",
      "verified": false,
      "sourceCount": 1,
      "_updatedAt": 1772783709057,
      "hash": "2f9a3f8d7126522cd82eea3d4f4ec585a2e8193b535ca1d45e03da8fd1f63421"
    },
    {
      "priority": "HIGH",
      "text": "United Arab Emirates travel advice - GOV.UK — FCDO travel advice for United Arab Emirates. Includes safety and security, insurance, entry requirements and legal differences.",
      "src": "UK FCDO",
      "impact": "자동 수집 반영",
      "tsIso": "2026-03-06T07:55:07.144Z",
      "ts": "2026-03-06 07:55",
      "verified": false,
      "sourceCount": 1,
      "_updatedAt": 1772783707144,
      "hash": "12bf701fc7c6442fc15acba57816dc04035873a44805e5419581b2bc30c8170b"
    },
    {
      "priority": "HIGH",
      "text": "United Arab Emirates Travel Advisory — Travel Advisories",
      "src": "US State Dept",
      "impact": "자동 수집 반영",
      "tsIso": "2026-03-06T07:55:06.874Z",
      "ts": "2026-03-06 07:55",
      "verified": false,
      "sourceCount": 1,
      "_updatedAt": 1772783706874,
      "hash": "feb8ff19e33c472bf0463b43816b21fb8fff10fa4d1b28cc0e61b2eb7727b5c5"
    },
    {
      "priority": "HIGH",
      "text": "Death toll in Israel’s Lebanon attacks over 120 as Beirut, south, east hit — Lebanon&#039;s Hezbollah group urges Israelis to evacuate border areas as Israel continues to bomb the country.",
      "src": "Al Jazeera / https://www.aljazeera.com/news/2026/3/6/death-toll-in-israels-lebanon-attacks-over-120-as-beirut-south-east-hit?traffic_source=rss",
      "impact": "자동 수집 반영",
      "tsIso": "2026-03-06T07:23:30.000Z",
      "ts": "2026-03-06 07:23",
      "verified": false,
      "sourceCount": 1,
      "_updatedAt": 1772781810000,
      "hash": "e2b51bd19abc2b7eed02a4a8858473277fa49265610354b4cd13b8c9b15d8e4c"
    }
  ],
  "indicators": [],
  "hypotheses": [],
  "routes": [],
  "checklist": [],
  "metadata": {
    "egressLossETA": 2
  }
}
