{
  "intelFeed": [
    {
      "priority": "LOW",
      "text": "View the overall status and health of AWS services using the AWS Health Dashboard.",
      "src": "AWS Health",
      "impact": "자동 수집 반영",
      "tsIso": "2026-03-22T23:47:50.571Z",
      "ts": "2026-03-22 23:47",
      "verified": false,
      "sourceCount": 1,
      "_updatedAt": 1774223270571,
      "hash": "94ad2c8f5b49f2b78c632be863690732b3e174dcae5e2e576e5fa053c005889a"
    },
    {
      "priority": "HIGH",
      "text": "Travel updates | Help | Emirates — Find out about the latest travel updates and any flight changes or cancellations. We update this page regularly with the most recent travel updates.",
      "src": "Emirates Airlines",
      "impact": "자동 수집 반영",
      "tsIso": "2026-03-22T23:47:50.359Z",
      "ts": "2026-03-22 23:47",
      "verified": false,
      "sourceCount": 1,
      "_updatedAt": 1774223270359,
      "hash": "3533ce5d03fc4876e320c99a27686f6fb2f5cfdfbc8b60d9092afbdca49d74c2"
    },
    {
      "priority": "HIGH",
      "text": "Home — The AIM Office provides a range of on-line services to ensure the availability of information required for safety, regularity and efficiency of international and national air navigation.",
      "src": "UAE GCAA",
      "impact": "자동 수집 반영",
      "tsIso": "2026-03-22T23:47:50.063Z",
      "ts": "2026-03-22 23:47",
      "verified": false,
      "sourceCount": 1,
      "_updatedAt": 1774223270063,
      "hash": "9bb114e21ad660eb884dde90e838089a23f859105188f090458ec3f89f0770ca"
    },
    {
      "priority": "HIGH",
      "text": "United Arab Emirates travel advice - GOV.UK — FCDO travel advice for United Arab Emirates. Includes safety and security, insurance, entry requirements and legal differences.",
      "src": "UK FCDO",
      "impact": "자동 수집 반영",
      "tsIso": "2026-03-22T23:47:48.394Z",
      "ts": "2026-03-22 23:47",
      "verified": false,
      "sourceCount": 1,
      "_updatedAt": 1774223268394,
      "hash": "e23efab0fa5cb7b5f64ba5e3d4395521abc016c4ca9dad5b2a43a93576bd30cf"
    },
    {
      "priority": "HIGH",
      "text": "United Arab Emirates Travel Advisory — Travel Advisories",
      "src": "US State Dept",
      "impact": "자동 수집 반영",
      "tsIso": "2026-03-22T23:47:47.310Z",
      "ts": "2026-03-22 23:47",
      "verified": false,
      "sourceCount": 1,
      "_updatedAt": 1774223267310,
      "hash": "5bf417f7fd4bbffbbd988d7d7fa4cb1b8ee89cf3fc8a36fc8c75ee2d8f7926c7"
    },
    {
      "priority": "LOW",
      "text": "View the overall status and health of AWS services using the AWS Health Dashboard.",
      "src": "AWS Health",
      "impact": "자동 수집 반영",
      "tsIso": "2026-03-22T23:16:58.722Z",
      "ts": "2026-03-22 23:16",
      "verified": false,
      "sourceCount": 1,
      "_updatedAt": 1774221418722,
      "hash": "5f024bb340815a59334a9483e4b9982f50c102e3393dc24c4468ffcb229e6f7b"
    },
    {
      "priority": "HIGH",
      "text": "Travel updates | Help | Emirates — Find out about the latest travel updates and any flight changes or cancellations. We update this page regularly with the most recent travel updates.",
      "src": "Emirates Airlines",
      "impact": "자동 수집 반영",
      "tsIso": "2026-03-22T23:16:58.214Z",
      "ts": "2026-03-22 23:16",
      "verified": false,
      "sourceCount": 1,
      "_updatedAt": 1774221418214,
      "hash": "119abe3091502bcae224efd1c8967d94c789000962e05602e122a8f5a91c2020"
    },
    {
      "priority": "HIGH",
      "text": "Home — The AIM Office provides a range of on-line services to ensure the availability of information required for safety, regularity and efficiency of international and national air navigation.",
      "src": "UAE GCAA",
      "impact": "자동 수집 반영",
      "tsIso": "2026-03-22T23:16:57.694Z",
      "ts": "2026-03-22 23:16",
      "verified": false,
      "sourceCount": 1,
      "_updatedAt": 1774221417694,
      "hash": "db583e2331b7664596047e71f04328a5ab4dc4e2be0a8a586ea42cc6feda952c"
    },
    {
      "priority": "HIGH",
      "text": "United Arab Emirates travel advice - GOV.UK — FCDO travel advice for United Arab Emirates. Includes safety and security, insurance, entry requirements and legal differences.",
      "src": "UK FCDO",
      "impact": "자동 수집 반영",
      "tsIso": "2026-03-22T23:16:55.535Z",
      "ts": "2026-03-22 23:16",
      "verified": false,
      "sourceCount": 1,
      "_updatedAt": 1774221415535,
      "hash": "26f7eee002b7c4aefb52dceb2d8e0b8ea017da87cfd911bcab5f20cc52c4deee"
    },
    {
      "priority": "HIGH",
      "text": "United Arab Emirates Travel Advisory — Travel Advisories",
      "src": "US State Dept",
      "impact": "자동 수집 반영",
      "tsIso": "2026-03-22T23:16:54.187Z",
      "ts": "2026-03-22 23:16",
      "verified": false,
      "sourceCount": 1,
      "_updatedAt": 1774221414187,
      "hash": "86de37f712942a4a71a1871e68e37fabc3529dfa00282231c8ca5fc45b805d66"
    },
    {
      "priority": "LOW",
      "text": "View the overall status and health of AWS services using the AWS Health Dashboard.",
      "src": "AWS Health",
      "impact": "자동 수집 반영",
      "tsIso": "2026-03-22T22:48:43.097Z",
      "ts": "2026-03-22 22:48",
      "verified": false,
      "sourceCount": 1,
      "_updatedAt": 1774219723097,
      "hash": "23a4ee463f0b354a8cff2fc83514c217916bcf2748e7afaa77e42cb32e32ee7e"
    },
    {
      "priority": "HIGH",
      "text": "Travel updates | Help | Emirates — Find out about the latest travel updates and any flight changes or cancellations. We update this page regularly with the most recent travel updates.",
      "src": "Emirates Airlines",
      "impact": "자동 수집 반영",
      "tsIso": "2026-03-22T22:48:42.773Z",
      "ts": "2026-03-22 22:48",
      "verified": false,
      "sourceCount": 1,
      "_updatedAt": 1774219722773,
      "hash": "637b7728a84be49628370894d858d71f7a60889d8372bb88b0ecc773dbf033c8"
    }
  ],
  "indicators": [],
  "hypotheses": [],
  "routes": [],
  "checklist": [],
  "metadata": {
    "egressLossETA": 2
  }
}
